hicberg/__init__.py
hicberg/__main__.py
hicberg/align.py
hicberg/benchmark.py
hicberg/eval.py
hicberg/io.py
hicberg/omics.py
hicberg/pipeline.py
hicberg/plot.py
hicberg/statistics.py
hicberg/utils.py
hicberg/version.py
hicberg/__pycache__/__init__.cpython-310.pyc
hicberg/__pycache__/__init__.cpython-311.pyc
hicberg/__pycache__/__init__.cpython-38.pyc
hicberg/__pycache__/__init__.cpython-39.pyc
hicberg/__pycache__/__main__.cpython-310.pyc
hicberg/__pycache__/__main__.cpython-311.pyc
hicberg/__pycache__/__main__.cpython-39.pyc
hicberg/__pycache__/align.cpython-310.pyc
hicberg/__pycache__/align.cpython-311.pyc
hicberg/__pycache__/align.cpython-38.pyc
hicberg/__pycache__/benchmark.cpython-310.pyc
hicberg/__pycache__/benchmark.cpython-311.pyc
hicberg/__pycache__/eval.cpython-310.pyc
hicberg/__pycache__/eval.cpython-311.pyc
hicberg/__pycache__/filter.cpython-311.pyc
hicberg/__pycache__/io.cpython-310.pyc
hicberg/__pycache__/io.cpython-311.pyc
hicberg/__pycache__/io.cpython-39.pyc
hicberg/__pycache__/pipeline.cpython-310.pyc
hicberg/__pycache__/pipeline.cpython-311.pyc
hicberg/__pycache__/plot.cpython-310.pyc
hicberg/__pycache__/plot.cpython-311.pyc
hicberg/__pycache__/statistics.cpython-310.pyc
hicberg/__pycache__/statistics.cpython-311.pyc
hicberg/__pycache__/statistics.cpython-39.pyc
hicberg/__pycache__/utils.cpython-310.pyc
hicberg/__pycache__/utils.cpython-311.pyc
hicberg/__pycache__/utils.cpython-39.pyc
hicberg/__pycache__/version.cpython-310.pyc
hicberg/__pycache__/version.cpython-311.pyc
tests/__init__.py
tests/conftest.py
tests/test_align.py
tests/test_benchmark.py
tests/test_eval.py
tests/test_io.py
tests/test_pipeline.py
tests/test_plot.py
tests/test_statistics.py
tests/test_utils.py
tests/__pycache__/__init__.cpython-311.pyc
tests/__pycache__/__init__.cpython-38.pyc
tests/__pycache__/conftest.cpython-311-pytest-7.4.0.pyc
tests/__pycache__/conftest.cpython-311-pytest-7.4.1.pyc
tests/__pycache__/conftest.cpython-311-pytest-7.4.3.pyc
hicberg-1.0.1.dist-info/LICENSE
hicberg-1.0.1.dist-info/METADATA
hicberg-1.0.1.dist-info/WHEEL
hicberg-1.0.1.dist-info/entry_points.txt
hicberg-1.0.1.dist-info/top_level.txt
hicberg-1.0.1.dist-info/RECORD
