Metadata-Version: 2.1
Name: hicberg
Version: 1.0.1
Summary: Standalone command line tool to visualize coverage from a BAM file
Home-page: https://github.com/sebgra/hicberg
Author: sgradit
Author-email: sebastien.gradit@pasteur.fr
License: MIT
Classifier: Development Status :: 3 - Alpha
Classifier: Intended Audience :: Science/Research
Classifier: Intended Audience :: Science/Research
Classifier: License :: OSI Approved :: MIT License
Classifier: Programming Language :: Python
Classifier: Programming Language :: Python :: 3
Classifier: Programming Language :: Python :: 3 :: Only
Classifier: Programming Language :: Python :: 3.11
Classifier: Topic :: Scientific/Engineering
Classifier: Topic :: Scientific/Engineering :: Bio-Informatics
Classifier: Topic :: Scientific/Engineering :: Visualization
Classifier: Operating System :: Microsoft :: Windows
Classifier: Operating System :: POSIX
Classifier: Operating System :: Unix
Classifier: Operating System :: MacOS
Requires-Python: >=3.11
License-File: LICENSE
Requires-Dist: bioframe
Requires-Dist: biopython
Requires-Dist: click
Requires-Dist: cooler
Requires-Dist: funcy
Requires-Dist: hicstuff
Requires-Dist: matplotlib
Requires-Dist: numpy
Requires-Dist: pandas
Requires-Dist: pysam
Requires-Dist: scipy
Requires-Dist: scikit-learn
Requires-Dist: statsmodels
